pipeline/__init__.py
pipeline/pipeline.py
easy_pipeline-0.0.1.dist-info/LICENSE
easy_pipeline-0.0.1.dist-info/METADATA
easy_pipeline-0.0.1.dist-info/WHEEL
easy_pipeline-0.0.1.dist-info/top_level.txt
easy_pipeline-0.0.1.dist-info/RECORD
